Metadata-Version: 2.1
Name: tttb
Version: 0.0.2a1
Summary: Tensor Train Toolbox in Python
Home-page: http://github.com/tmolteno/tttb
Author: Tim Molteno
Author-email: tim@elec.ac.nz
License: GPLv3
Platform: UNKNOWN
Classifier: Development Status :: 4 - Beta
Classifier: Topic :: Scientific/Engineering
Classifier: License :: OSI Approved :: GNU General Public License v3 (GPLv3)
Classifier: Programming Language :: Python :: 2
Classifier: Programming Language :: Python :: 2.7
Classifier: Programming Language :: Python :: 3
Classifier: Programming Language :: Python :: 3.7
Classifier: Intended Audience :: Science/Research
